pulmo_cristal/__init__.py
pulmo_cristal/cli.py
pulmo_cristal/exporters/__init__.py
pulmo_cristal/exporters/csv_exporter.py
pulmo_cristal/exporters/json_exporter.py
pulmo_cristal/extractors/__init__.py
pulmo_cristal/extractors/base.py
pulmo_cristal/extractors/hla.py
pulmo_cristal/extractors/patterns.py
pulmo_cristal/extractors/pdf.py
pulmo_cristal/models/__init__.py
pulmo_cristal/models/donneurs.py
pulmo_cristal/utils/__init__.py
pulmo_cristal/utils/file_utils.py
pulmo_cristal/utils/logging.py
tests/__init__.py
tests/conftest.py
tests/test_cli.py
tests/test_exporters/__init__.py
tests/test_exporters/test_csv_exporter.py
tests/test_exporters/test_json_exporter.py
tests/test_extractors/__init__.py
tests/test_extractors/test_base.py
tests/test_extractors/test_hla.py
tests/test_extractors/test_patterns.py
tests/test_extractors/test_pdf.py
tests/test_models/__init__.py
tests/test_models/test_donneur.py
tests/test_utils/__init__.py
tests/test_utils/test_file_utils.py
tests/test_utils/test_logging.py
pulmo_cristal-0.1.0.dist-info/LICENSE
pulmo_cristal-0.1.0.dist-info/METADATA
pulmo_cristal-0.1.0.dist-info/WHEEL
pulmo_cristal-0.1.0.dist-info/entry_points.txt
pulmo_cristal-0.1.0.dist-info/top_level.txt
pulmo_cristal-0.1.0.dist-info/RECORD
