Metadata-Version: 2.2
Name: pulmo-cristal
Version: 0.1.0
Summary: Extract data from donor PDF documents for pulmonary transplantation
Requires-Python: >=3.8
License-File: LICENSE
Requires-Dist: PyPDF2>=3.0.0
Requires-Dist: camelot-py>=1.0.0
Requires-Dist: PyPDF2>=3.0.0
Requires-Dist: opencv-python-headless>=4.5.0
Requires-Dist: ghostscript>=0.7
Requires-Dist: numpy>=1.20.0
Requires-Dist: pandas>=1.3.0
Provides-Extra: dev
Requires-Dist: pytest>=7.0.0; extra == "dev"
Requires-Dist: pytest-cov>=4.0.0; extra == "dev"
Dynamic: provides-extra
Dynamic: requires-dist
Dynamic: requires-python
Dynamic: summary
